models/__init__.py
models/config.py
models/model_add.py
yrag/__init__.py
yrag/yrag_cli.py
yrag/template/Dockerfile
yrag/template/__init__.py
yrag/template/app/__init__.py
yrag/template/app/main.py
yrag-0.1.5.dist-info/LICENSE
yrag-0.1.5.dist-info/METADATA
yrag-0.1.5.dist-info/WHEEL
yrag-0.1.5.dist-info/entry_points.txt
yrag-0.1.5.dist-info/top_level.txt
yrag-0.1.5.dist-info/RECORD
