Metadata-Version: 2.1
Name: yrag
Version: 0.1.5
Summary: Yrag aim to deploy machine-learing model quickly and easily
Home-page: https://github.com/Yougigun/yrag
Author: Gary
Author-email: s14031403@gmail.com
License: UNKNOWN
Platform: UNKNOWN
Classifier: Programming Language :: Python :: 3
Classifier: License :: OSI Approved :: MIT License
Classifier: Operating System :: OS Independent
Requires-Python: >=3.6
